apiStock/__init__.py
apiStock/__version__.py
apiStock/const.py
apiStock/core.py
apiStock/test.py
apiStock-0.8.dist-info/LICENSE
apiStock-0.8.dist-info/METADATA
apiStock-0.8.dist-info/WHEEL
apiStock-0.8.dist-info/top_level.txt
apiStock-0.8.dist-info/RECORD
