Metadata-Version: 2.1
Name: apiStock
Version: 0.8
Summary: Api useful to get stock data
Home-page: https://github.com/thanhtlx/api-stock
Author: thanhtlx
Author-email: thanh1908.xx@gmail.com
License: MIT
Keywords: api,stock,stock vietnam,historical stock
Platform: UNKNOWN
Classifier: Development Status :: 3 - Alpha
Classifier: Topic :: Software Development :: Build Tools
Classifier: License :: OSI Approved :: MIT License
Classifier: Programming Language :: Python :: 3
Classifier: Programming Language :: Python :: 3.4
Classifier: Programming Language :: Python :: 3.5
Classifier: Programming Language :: Python :: 3.6
Classifier: Programming Language :: Python :: 3.7
Classifier: Programming Language :: Python :: 3.8
Classifier: Programming Language :: Python :: 3.9
Requires-Python: >=3.6.0
Requires-Dist: requests
